sql_records/__init__.py
sql_records/connection.py
sql_records/table.py
sql_records/utils.py
sql_records-1.0.0.dist-info/METADATA
sql_records-1.0.0.dist-info/WHEEL
sql_records-1.0.0.dist-info/top_level.txt
sql_records-1.0.0.dist-info/RECORD
