Metadata-Version: 2.1
Name: sql-records
Version: 1.0.0
Summary: small mysql tool
Home-page: UNKNOWN
Author: zlqm
Author-email: UNKNOWN
License: UNKNOWN
Platform: UNKNOWN
Classifier: Programming Language :: Python :: 3
Classifier: Operating System :: OS Independent
Requires-Dist: pymysql
Requires-Dist: tablib
